sqwish/__init__.py
sqwish-0.0.0.dist-info/METADATA
sqwish-0.0.0.dist-info/WHEEL
sqwish-0.0.0.dist-info/top_level.txt
sqwish-0.0.0.dist-info/RECORD
