Metadata-Version: 2.1
Name: sqwish
Version: 0.0.0
Summary: Coming soon
Author-email: Federica <federica@sqwish.ai>
